{
	"name": "pipeline1",
	"properties": {
		"activities": [
			{
				"name": "Wait1",
				"type": "Wait",
				"dependsOn": [],
				"userProperties": [],
				"typeProperties": {
					"waitTimeInSeconds": 1
				}
			},
			{
				"name": "Get Metadata1",
				"type": "GetMetadata",
				"dependsOn": [
					{
						"activity": "Set variable1",
						"dependencyConditions": [
							"Succeeded"
						]
					}
				],
				"policy": {
					"timeout": "0.12:00:00",
					"retry": 0,
					"retryIntervalInSeconds": 30,
					"secureOutput": false,
					"secureInput": false
				},
				"userProperties": [],
				"typeProperties": {
					"dataset": {
						"referenceName": "DelimitedText3",
						"type": "DatasetReference",
						"parameters": {
							"fileName": {
								"value": "@variables('filename')",
								"type": "Expression"
							}
						}
					},
					"fieldList": [
						"exists"
					],
					"storeSettings": {
						"type": "AzureBlobFSReadSettings",
						"recursive": true,
						"enablePartitionDiscovery": false
					},
					"formatSettings": {
						"type": "DelimitedTextReadSettings"
					}
				}
			},
			{
				"name": "If Condition1",
				"type": "IfCondition",
				"dependsOn": [
					{
						"activity": "Get Metadata1",
						"dependencyConditions": [
							"Succeeded"
						]
					}
				],
				"userProperties": [],
				"typeProperties": {
					"expression": {
						"value": "@activity('Get Metadata1').output.exists",
						"type": "Expression"
					},
					"ifFalseActivities": [
						{
							"name": "Data flow2",
							"type": "ExecuteDataFlow",
							"dependsOn": [],
							"policy": {
								"timeout": "0.12:00:00",
								"retry": 0,
								"retryIntervalInSeconds": 30,
								"secureOutput": false,
								"secureInput": false
							},
							"userProperties": [],
							"typeProperties": {
								"dataflow": {
									"referenceName": "dataflow1",
									"type": "DataFlowReference",
									"parameters": {
										"ADFName": {
											"value": "'@{pipeline().DataFactory}'",
											"type": "Expression"
										},
										"Pipeline": {
											"value": "'@{pipeline().Pipeline}'",
											"type": "Expression"
										},
										"Status": {
											"value": "'@{pipeline().Pipeline}'",
											"type": "Expression"
										},
										"RunId": {
											"value": "'@{pipeline().RunId}'",
											"type": "Expression"
										},
										"TriggerName": {
											"value": "'@{pipeline().TriggerName}'",
											"type": "Expression"
										},
										"logFileName": {
											"value": "'@{variables('filename')}'",
											"type": "Expression"
										}
									}
								},
								"compute": {
									"coreCount": 8,
									"computeType": "General"
								},
								"traceLevel": "Fine"
							}
						}
					],
					"ifTrueActivities": [
						{
							"name": "Data flow1",
							"type": "ExecuteDataFlow",
							"dependsOn": [],
							"policy": {
								"timeout": "0.12:00:00",
								"retry": 0,
								"retryIntervalInSeconds": 30,
								"secureOutput": false,
								"secureInput": false
							},
							"userProperties": [],
							"typeProperties": {
								"dataflow": {
									"referenceName": "dataflow1_copy1",
									"type": "DataFlowReference",
									"parameters": {
										"ADFName": {
											"value": "'@{pipeline().DataFactory}'",
											"type": "Expression"
										},
										"Pipeline": {
											"value": "'@{pipeline().Pipeline}'",
											"type": "Expression"
										},
										"Status": {
											"value": "'@{pipeline().Pipeline}'",
											"type": "Expression"
										},
										"RunId": {
											"value": "'@{pipeline().RunId}'",
											"type": "Expression"
										},
										"TriggerName": {
											"value": "'@{pipeline().TriggerName}'",
											"type": "Expression"
										},
										"logFileName": {
											"value": "'@{variables('filename')}'",
											"type": "Expression"
										}
									},
									"datasetParameters": {
										"source2": {
											"fileName": {
												"value": "@variables('filename')",
												"type": "Expression"
											}
										}
									}
								},
								"compute": {
									"coreCount": 8,
									"computeType": "General"
								},
								"traceLevel": "Fine"
							}
						}
					]
				}
			},
			{
				"name": "Set variable1",
				"type": "SetVariable",
				"dependsOn": [
					{
						"activity": "Wait1",
						"dependencyConditions": [
							"Completed"
						]
					}
				],
				"policy": {
					"secureOutput": false,
					"secureInput": false
				},
				"userProperties": [],
				"typeProperties": {
					"variableName": "filename",
					"value": {
						"value": "@concat(formatDateTime(utcNow(),'yyyy-MM-dd'),'_log.csv')",
						"type": "Expression"
					}
				}
			}
		],
		"variables": {
			"filename": {
				"type": "String"
			}
		},
		"annotations": []
	}
}